DESCRIPTION
MANIFEST.in
README
README.rst
setup.py
adminstat/__init__.py
adminstat/admin.py
adminstat/models.py
django_adminstat.egg-info/PKG-INFO
django_adminstat.egg-info/SOURCES.txt
django_adminstat.egg-info/dependency_links.txt
django_adminstat.egg-info/not-zip-safe
django_adminstat.egg-info/requires.txt
django_adminstat.egg-info/top_level.txt