Metadata-Version: 1.0
Name: django-adminstat
Version: 0.1.0
Summary: Simple app, provides django's LogEntry objects admin. It can be used to collect inforabout staff users actions on site
Home-page: UNKNOWN
Author: Ivan Gromov
Author-email: ivan.gromov@redsolution.ru
License: AGPLv3
Keywords: django admin log
Platform: UNKNOWN
Classifier: Development Status :: 3 - Alpha
Classifier: Environment :: Web Environment
Classifier: Framework :: Django
Classifier: Intended Audience :: Developers
Classifier: License :: OSI Approved :: GNU Affero General Public License v3
Classifier: Natural Language :: Russian
Classifier: Topic :: Internet :: WWW/HTTP :: Site Management
Classifier: Topic :: Utilities
